deposit_amount.py
home_loan.py
personal_loan.py
vehicle_loan.py
withdraw_amount.py
bank2-0.0.1.dist-info/License.txt
bank2-0.0.1.dist-info/METADATA
bank2-0.0.1.dist-info/WHEEL
bank2-0.0.1.dist-info/top_level.txt
bank2-0.0.1.dist-info/RECORD
